README.md
setup.cfg
setup.py
examples/__init__.py
examples/classification.py
ldr/__init__.py
ldr/utils.py
ldr.egg-info/PKG-INFO
ldr.egg-info/SOURCES.txt
ldr.egg-info/dependency_links.txt
ldr.egg-info/requires.txt
ldr.egg-info/top_level.txt
tests/__init__.py
tests/conftest.py
tests/test_entry.py
tests/test_examples.py
tests/test_utils.py