Metadata-Version: 2.1
Name: ldr
Version: 0.6
Summary: Latent Dimensionality Reduction in Python
Home-page: https://github.com/ekrekr/pyldr
Author: Elias Kassell
Author-email: eliaskassell@gmail.com
License: UNKNOWN
Keywords: visualization
Platform: UNKNOWN
Classifier: Development Status :: 3 - Alpha
Classifier: Intended Audience :: Developers
Classifier: Topic :: Scientific/Engineering :: Visualization
Classifier: License :: OSI Approved :: GNU General Public License v3 (GPLv3)
Classifier: Operating System :: OS Independent
Classifier: Programming Language :: Python :: 3
Requires-Python: >3.5
Provides-Extra: dev
Provides-Extra: test
